coresets/__init__.py
coresets/algorithms/__init__.py
coresets/algorithms/wbgm.py
coresets/algorithms/weighted_kmeans.py
coresets/algorithms/wgm.py
coresets/coreset.py
coresets/k_means_coreset.py
coresets/utils/__init__.py
coresets/utils/datagen.py
coresets/utils/kmeans_init.py
coresets/utils/plotting.py
coresets/algorithms/weighted_kmeans_.cpython-38-x86_64-linux-gnu.so
coresets/sensitivity.cpython-38-x86_64-linux-gnu.so
coresets-0.2.0.dist-info/LICENSE
coresets-0.2.0.dist-info/METADATA
coresets-0.2.0.dist-info/WHEEL
coresets-0.2.0.dist-info/RECORD
