Metadata-Version: 2.1
Name: coresets
Version: 0.2.0
Summary: Coreset generation for k-Means and (Bayesian) Gaussian mixture models
Home-page: https://github.com/ashtuchkin/coresets
License: BSD-3-Clause
Author: Zalán Borsos
Author-email: zalan.borsos@inf.ethz.ch
Requires-Python: >=3.8,<4.0
Classifier: License :: OSI Approved :: BSD License
Classifier: Programming Language :: Python :: 3
Classifier: Programming Language :: Python :: 3.8
Classifier: Programming Language :: Python :: 3.9
Classifier: Programming Language :: Python :: 3.10
Classifier: Programming Language :: Python :: 3.11
Requires-Dist: numpy (>=1.14,<2.0)
Requires-Dist: scikit-learn (>=1.0,<2.0)
Project-URL: Repository, https://github.com/ashtuchkin/coresets
